pymsbuild/dllpack.py
pymsbuild/_locate_vs.py
pymsbuild/_init.py
pymsbuild/_load_sysconfig.py
pymsbuild/pyproject.toml.in
pymsbuild/_build.py
pymsbuild/cython.py
pymsbuild/_generate.py
pymsbuild/_types.py
pymsbuild/_msbuild.py.in
pymsbuild/entrypoint.py
pymsbuild/_tags.py
pymsbuild/__main__.py
pymsbuild/_writer.py
pymsbuild/vendor.py
pymsbuild/_locate_dotnet.py
pymsbuild/__init__.py
pymsbuild/targets/dllpack_main.py
pymsbuild/targets/package.targets
pymsbuild/targets/runtime-windows.targets
pymsbuild/targets/cpp-ARM.props
pymsbuild/targets/cpp-ARM.targets
pymsbuild/targets/cpp-Win32.props
pymsbuild/targets/entrypoint-windows.cpp
pymsbuild/targets/sdist.targets
pymsbuild/targets/dllpack.targets
pymsbuild/targets/cython.targets
pymsbuild/targets/common.targets
pymsbuild/targets/cpp-x64.props
pymsbuild/targets/dllpack-gcc.h
pymsbuild/targets/cpp-POSIX_x64.targets
pymsbuild/targets/runtime-gcc.targets
pymsbuild/targets/dllpack-generate.py
pymsbuild/targets/pyd.targets
pymsbuild/targets/cpp-ARM64.props
pymsbuild/targets/cpp-default-Win32.props
pymsbuild/targets/runtime-download.py
pymsbuild/targets/cpp-x64.targets
pymsbuild/targets/entrypoint-windows.rc
pymsbuild/targets/package.override.targets
pymsbuild/targets/cpp-default-POSIX_x64.props
pymsbuild/targets/cpp-ARM64.targets
pymsbuild/targets/cpp-default-x64.props
pymsbuild/targets/cpp-default-ARM.props
pymsbuild/targets/cpp-Win32.targets
pymsbuild/targets/runtime.targets
pymsbuild/targets/cpp-default-ARM64.props
pymsbuild/targets/dllpack-windows.h
pymsbuild/targets/package.props
pymsbuild/targets/entrypoint-gcc.c
pymsbuild/targets/pyd.props
pymsbuild/targets/dllpack-gcc.targets
pymsbuild/targets/entrypoint.targets
pymsbuild/targets/entrypoint.props
pymsbuild/targets/cpp-POSIX_x64-GCC.props
pymsbuild/targets/dllpack.c
pymsbuild/targets/common.props
pymsbuild/targets/cpp-POSIX_x64.props
pymsbuild-1.2.1.dist-info/METADATA
pymsbuild-1.2.1.dist-info/WHEEL
pymsbuild-1.2.1.dist-info/RECORD