Metadata-Version: 2.2
Name: pymsbuild
Version: 1.2.1
Author: Steve Dower
Author-email: steve.dower@python.org
Project-url: Homepage, https://github.com/zooba/pymsbuild
Project-url: Source, https://github.com/zooba/pymsbuild
Project-url: Issues, https://github.com/zooba/pymsbuild/issues
Summary: The pymsbuild build backend.
Keywords: build,pep-517,msbuild,packaging,cython
Classifier: Development Status :: 5 - Production/Stable
Classifier: Intended Audience :: Developers
Classifier: License :: OSI Approved :: MIT License
Classifier: Operating System :: Microsoft :: Windows
Classifier: Operating System :: POSIX :: Linux
Classifier: Programming Language :: Python :: 3.8
Classifier: Programming Language :: Python :: 3.9
Classifier: Programming Language :: Python :: 3.10
Classifier: Programming Language :: Python :: 3.11
Classifier: Programming Language :: Python :: 3.12
Classifier: Topic :: Software Development :: Build Tools
Classifier: Topic :: Software Development :: Compilers
Classifier: Topic :: Utilities
Requires-External: msbuild,dotnet
Requires-Dist: packaging
